{"lasso": {"num_features": 74, "roc_val": 0.6958593264570647, "features": ["precipIntensity", "precipProbability", "temperature", "apparentTemperature", "dewPoint", "cloudCover", "uvIndex", "hora_0", "hora_1", "hora_2", "hora_3", "hora_4", "hora_5", "hora_6", "hora_7", "hora_8", "hora_9", "hora_10", "hora_14", "hora_15", "hora_16", "hora_17", "hora_18", "hora_19", "hora_20", "hora_21", "hora_22", "hora_23", "icon_clear-day", "icon_cloudy", "icon_fog", "icon_partly-cloudy-day", "icon_rain", "dia_sem_0", "dia_sem_1", "dia_sem_3", "dia_sem_4", "dia_sem_6", "festivo", "cloudCover_mean", "dewPoint_mean", "humidity_mean", "precipIntensity_mean", "visibility_mean", "windSpeed_mean", "cloudCover_mean_forward", "dewPoint_mean_forward", "humidity_mean_forward", "precipIntensity_mean_forward", "visibility_mean_forward", "windSpeed_mean_forward", "cumAcc_1D", "cumAcc_3D", "cumAcc_7D", "poblado_alejandria", "poblado_altosdelpoblado", "poblado_astorga", "poblado_barriocolombia", "poblado_castropol", "poblado_elcastillo", "poblado_eldiamanteno2", "poblado_elpoblado", "poblado_eltesoro", "poblado_laaguacatala", "poblado_lalinde", "poblado_laslomasno1", "poblado_laslomasno2", "poblado_losbalsosno1", "poblado_losbalsosno2", "poblado_losnaranjos", "poblado_manila", "poblado_patiobonito", "poblado_sanlucas", "poblado_villacarlota"]}, "forward": {"num_features": 33, "roc_val": 0.7335802162296508, "features": ["precipIntensity", "temperature", "uvIndex", "visibility", "hora_0", "hora_1", "hora_2", "hora_3", "hora_4", "hora_5", "hora_7", "hora_12", "hora_13", "hora_16", "hora_23", "icon_clear-night", "icon_rain", "dia_sem_4", "festivo", "Mes_Junio", "Year_2017", "temperature_mean", "visibility_mean", "apparentTemperature_mean_forward", "cloudCover_mean_forward", "humidity_mean_forward", "temperature_mean_forward", "cumAcc_3D", "cumAcc_60D", "poblado_astorga", "poblado_elcastillo", "poblado_laaguacatala", "poblado_losnaranjos"]}, "AG": {"num_features": 51, "roc_val": 0.7220280850006214, "features": ["precipProbability", "temperature", "humidity", "cloudCover", "visibility", "hora_1", "hora_3", "hora_4", "hora_7", "hora_8", "hora_9", "hora_10", "hora_13", "hora_14", "hora_16", "hora_17", "hora_18", "hora_19", "hora_21", "hora_22", "icon_cloudy", "icon_fog", "icon_rain", "dia_sem_3", "dia_sem_4", "dia_sem_6", "Mes_Junio", "Year_2017", "apparentTemperature_mean", "cloudCover_mean", "humidity_mean", "temperature_mean", "visibility_mean", "dewPoint_mean_forward", "precipIntensity_mean_forward", "windSpeed_mean_forward", "cumAcc_7D", "cumAcc_14D", "cumAcc_60D", "poblado_alejandria", "poblado_barriocolombia", "poblado_castropol", "poblado_eldiamanteno2", "poblado_laaguacatala", "poblado_lalinde", "poblado_laslomasno1", "poblado_laslomasno2", "poblado_losbalsosno2", "poblado_patiobonito", "poblado_sanlucas", "poblado_santamariadelosangeles"]}}